AUTHORS
ChangeLog
LICENSE
Pipfile
README.rst
requirements.txt
setup.cfg
setup.py
images/mutextree-qualified-name.png
images/mutextree-step1.png
images/mutextree-step2.png
images/mutextree-step3.png
images/mutextree-step4.png
images/mutextree-step5.png
images/mutextree-voc.png
mutextree/__init__.py
mutextree.egg-info/PKG-INFO
mutextree.egg-info/SOURCES.txt
mutextree.egg-info/dependency_links.txt
mutextree.egg-info/not-zip-safe
mutextree.egg-info/pbr.json
mutextree.egg-info/requires.txt
mutextree.egg-info/top_level.txt
test/__init__.py
test/test_mutex.py