Metadata-Version: 1.1
Name: mutextree
Version: 1.2.3
Summary: Protect tree-like resources
Home-page: https://github.com/SewanDevs/mutextree
Author: Adrian Vandier Ast
Author-email: adrian.vandierast@sewan.fr
License: UNKNOWN
Platform: UNKNOWN
Classifier: Development Status :: 4 - Beta
Classifier: Intended Audience :: Information Technology
Classifier: Intended Audience :: Developers
Classifier: License :: OSI Approved :: Mozilla Public License 2.0 (MPL 2.0)
Classifier: Operating System :: OS Independent
Classifier: Programming Language :: Python
Classifier: Programming Language :: Python :: 2
Classifier: Programming Language :: Python :: 2.7
Classifier: Programming Language :: Python :: 3
Classifier: Programming Language :: Python :: 3.6
